{
  "title": "I led a team of engineers expanding customer care capabilities and built a bridge to modernize a (very) legacy tech stack.",
  "description": "I led a team of engineers expanding customer care capabilities and built a bridge to modernize a (very) legacy tech stack.",
  "image": "/og-share.png",
  "published": true,
  "featured": true,
  "tags": ["american-express"],
  "company": "American Express",
  "startDate": "2020-03-01T00:00:00.000Z",
  "endDate": "",
  "createdAt": "2024-06-27T20:10:42.191Z",
  "type": "work"
}
